torutils/__init__.py
torutils/config.py
torutils/torconnect.py
torutils-0.0.2.dist-info/LICENSE
torutils-0.0.2.dist-info/METADATA
torutils-0.0.2.dist-info/WHEEL
torutils-0.0.2.dist-info/top_level.txt
torutils-0.0.2.dist-info/RECORD
