Metadata-Version: 2.1
Name: torutils
Version: 0.0.2
Summary: Tor Proxying Library to spin multiple Tor connections
Author-email: Rommel Rodriguez Perez <alrodperez@gmail.com>
License: Copyright (c) 2018 The Python Packaging Authority        
Project-URL: Homepage, https://github.com/rommel-rodriguez/torutils/
Project-URL: Bug Tracker, https://github.com/rommel-rodriguez/torutils/issues
Classifier: Programming Language :: Python :: 3
Classifier: License :: OSI Approved :: MIT License
Classifier: Operating System :: OS Independent
Requires-Python: >=3.7
License-File: LICENSE
